{
  "aliases": [],
  "arguments": [],
  "description": "5. Get the reputation of an IP address",
  "examples": [
    "Command Example\n!ip ip=\"8.8.3.3\"\nContext Example\n{\n\"IP\": [\n{\n\"Malicious\": {\n\"Vendor\": \"MISP.ORGNAME\",",
    "!ip ip=\"8.8.3.3\"\nContext Example\n{\n\"IP\": [\n{\n\"Malicious\": {\n\"Vendor\": \"MISP.ORGNAME\",\n\"Description\": \"IP Found in MISP event: 743\""
  ],
  "kind": "integration-command",
  "name": "ip",
  "notes": [],
  "outputs": [
    {
      "description": "Bad IP address found. IP.Malicious.Vendor For malicious IPs, the vendor that made the decision.",
      "name": "IP.Address",
      "required": ""
    },
    {
      "description": "For malicious IPs, the reason that the vendor made the decision. DBotScore.Indicator The indicator that was tested.",
      "name": "IP.Malicious.Description",
      "required": ""
    },
    {
      "description": "Indicator type. DBotScore.Vendor The vendor used to calculate the score.",
      "name": "DBotScore.Type",
      "required": ""
    },
    {
      "description": "The actual score.",
      "name": "DBotScore.Score",
      "required": ""
    }
  ],
  "retrieved_at": "2026-04-22T15:02:53+00:00",
  "source_title": "MISP v2 (Deprecated)",
  "source_url": "https://xsoar.pan.dev/docs/reference/integrations/misp-v2"
}
