{
  "aliases": [],
  "arguments": [],
  "description": "Human Readable Output",
  "examples": [
    "Command Example\n!qradar-get-search-results search_id=14b1d702-edba-43e7-b01c-36f8da1ed016 range=0-0\nContext Example\n{\n\"QRadar\": {\n\"Search\": {\n\"Result\": {\n\"events\": [",
    "!qradar-get-search-results search_id=14b1d702-edba-43e7-b01c-36f8da1ed016 range=0-0\nContext Example\n{\n\"QRadar\": {\n\"Search\": {\n\"Result\": {\n\"events\": [\n{"
  ],
  "kind": "integration-command",
  "name": "qradar-get-search-results",
  "notes": [],
  "outputs": [
    {
      "description": "The result of the search",
      "name": "QRadar.Search.Result",
      "required": ""
    }
  ],
  "retrieved_at": "2026-04-22T15:02:53+00:00",
  "source_title": "IBM QRadar (Deprecated)",
  "source_url": "https://xsoar.pan.dev/docs/reference/integrations/q-radar"
}
