{
  "aliases": [],
  "arguments": [
    {
      "description": "",
      "name": "There are no input arguments for this command.",
      "required": ""
    }
  ],
  "description": "confluence-cloud-oauth-test",
  "examples": [
    "!\nconfluence-cloud-oauth-test\nEdit this page\nReport an Issue\nPrevious\n\u00ab Atlassian Cloud MCP\nNext\nAtlassian Confluence Server \u00bb"
  ],
  "kind": "integration-command",
  "name": "#",
  "notes": [],
  "outputs": [
    {
      "description": "",
      "name": "There is no context output for this command.",
      "required": ""
    }
  ],
  "retrieved_at": "2026-04-22T15:02:53+00:00",
  "source_title": "Atlassian Confluence Cloud",
  "source_url": "https://xsoar.pan.dev/docs/reference/integrations/atlassian-confluence-cloud"
}
