{
  "aliases": [],
  "arguments": [],
  "description": "Get an event by event ID: sigsci-get-event-by-id",
  "examples": [
    "Command Example\n!sigsci-get-whitelist siteName=demisto\nContext Example\n{\n\"SigSciences.Corp.Site.Whitelist\": [\n{\n\"ExpiryDate\": \"\",\n\"Note\": \"docdoc\",",
    "!sigsci-get-whitelist siteName=demisto\nContext Example\n{\n\"SigSciences.Corp.Site.Whitelist\": [\n{\n\"ExpiryDate\": \"\",\n\"Note\": \"docdoc\",\n\"Source\": \"9.7.9.7\","
  ],
  "kind": "integration-command",
  "name": "sigsci-get-whitelist",
  "notes": [],
  "outputs": [
    {
      "description": "ID for this particular entry. SigSciences.Corp.Site.Whitelist.Source IP Address present in the allow list.",
      "name": "SigSciences.Corp.Site.Whitelist.ID",
      "required": ""
    },
    {
      "description": "date Expiration Timestamp. SigSciences.Corp.Site.Whitelist.Note",
      "name": "SigSciences.Corp.Site.Whitelist.ExpiryDate",
      "required": ""
    },
    {
      "description": "Note associated with the tag. SigSciences.Corp.Site.Whitelist.CreatedDate date",
      "name": "string",
      "required": ""
    },
    {
      "description": "SigSciences.Corp.Site.Whitelist.CreatedBy The user who added this source.",
      "name": "The created date timestamp",
      "required": ""
    }
  ],
  "retrieved_at": "2026-04-22T15:02:53+00:00",
  "source_title": "Signal Sciences WAF",
  "source_url": "https://xsoar.pan.dev/docs/reference/integrations/signal-sciences-waf"
}
