{
  "aliases": [
    "email-ask-user"
  ],
  "arguments": [],
  "description": "EmailAskUser | Cortex XSOAR",
  "examples": [],
  "kind": "script",
  "name": "EmailAskUser",
  "notes": [],
  "outputs": [
    {
      "description": "Prerequisites",
      "name": "There are no outputs for this script.",
      "required": ""
    },
    {
      "description": "Troubleshooting",
      "name": "Requires an instance of one of the available email integrations, set to fetch incidents.",
      "required": ""
    },
    {
      "description": "Notes",
      "name": "In case that the incident in which the automation script is running, has limited permissions to (e.g. has a certain role assigned to it), then the responder to the email need to have the relevant permissions assigned to its user in Cortex XSOAR.",
      "required": ""
    },
    {
      "description": "will not work when run in the playbook debugger. This is because the debugger does not generate entitlements, since they must be tied to an investigation. Entitlements are needed to track the response. Whitespaces are not supported in custom options and will not work. (i.e. setting a button to I Agree",
      "name": "EmailAskUser",
      "required": ""
    },
    {
      "description": "Edit this page Report an Issue Previous",
      "name": ")",
      "required": ""
    },
    {
      "description": "Next EmailAskUserResponse \u00bb Setup",
      "name": "\u00ab EditServerConfig",
      "required": ""
    },
    {
      "description": "Step 2 - A conditional task Example Script Data",
      "name": "Step 1 - Sending an email",
      "required": ""
    },
    {
      "description": "Troubleshooting Notes Docs",
      "name": "Prerequisites",
      "required": ""
    },
    {
      "description": "Become a Technology Partner Social Blog",
      "name": "Developer Docs",
      "required": ""
    },
    {
      "description": "",
      "name": "Copyright \u00a9 2026 Palo Alto Networks, Inc.",
      "required": ""
    }
  ],
  "retrieved_at": "2026-04-22T15:02:53+00:00",
  "source_title": "EmailAskUser",
  "source_url": "https://xsoar.pan.dev/docs/reference/scripts/email-ask-user"
}
