{
  "aliases": [
    "jira-v3-convert-comments-to-table"
  ],
  "arguments": [
    {
      "description": "",
      "name": "There are no inputs for this script.",
      "required": ""
    }
  ],
  "description": "JiraV3ConvertCommentsToTable | Cortex XSOAR",
  "examples": [],
  "kind": "script",
  "name": "JiraV3ConvertCommentsToTable",
  "notes": [],
  "outputs": [
    {
      "description": "Edit this page Report an Issue Previous",
      "name": "There are no outputs for this script.",
      "required": ""
    },
    {
      "description": "Next JiraV3ConvertSubtasksToTable \u00bb Script Data",
      "name": "\u00ab JiraV3ConvertAttachmentsToTable",
      "required": ""
    },
    {
      "description": "Developer Docs Become a Technology Partner Social",
      "name": "Docs",
      "required": ""
    },
    {
      "description": "Copyright \u00a9 2026 Palo Alto Networks, Inc.",
      "name": "Blog",
      "required": ""
    }
  ],
  "retrieved_at": "2026-04-22T15:02:53+00:00",
  "source_title": "JiraV3ConvertCommentsToTable",
  "source_url": "https://xsoar.pan.dev/docs/reference/scripts/jira-v3-convert-comments-to-table"
}
