{
  "aliases": [
    "out-of-office-list-cleanup"
  ],
  "arguments": [],
  "description": "OutOfOfficeListCleanup | Cortex XSOAR",
  "examples": [],
  "kind": "script",
  "name": "OutOfOfficeListCleanup",
  "notes": [],
  "outputs": [
    {
      "description": "Edit this page Report an Issue Previous",
      "name": "There are no outputs for this script.",
      "required": ""
    },
    {
      "description": "Next PadZeros \u00bb Script Data",
      "name": "\u00ab Osxcollector",
      "required": ""
    },
    {
      "description": "Developer Docs Become a Technology Partner Social",
      "name": "Docs",
      "required": ""
    },
    {
      "description": "Copyright \u00a9 2026 Palo Alto Networks, Inc.",
      "name": "Blog",
      "required": ""
    }
  ],
  "retrieved_at": "2026-04-22T15:02:53+00:00",
  "source_title": "OutOfOfficeListCleanup",
  "source_url": "https://xsoar.pan.dev/docs/reference/scripts/out-of-office-list-cleanup"
}
