{
  "aliases": [
    "risk-iq-passive-total-trackers-script"
  ],
  "arguments": [],
  "description": "RiskIQPassiveTotalTrackersScript | Cortex XSOAR",
  "examples": [
    "!RiskIQPassiveTotalTrackersScript indicator_value=filmesonlinegratis.net\nContext Example\n#\n{\n\"DBotScore\": [\n{\n\"Indicator\": \"filmesonlinegratis.net\",\n\"Score\": 0,"
  ],
  "kind": "script",
  "name": "RiskIQPassiveTotalTrackersScript",
  "notes": [],
  "outputs": [
    {
      "description": "Script Example",
      "name": "There are no outputs for this script.",
      "required": ""
    },
    {
      "description": "Context Example",
      "name": "!RiskIQPassiveTotalTrackersScript indicator_value=filmesonlinegratis.net",
      "required": ""
    },
    {
      "description": "\"DBotScore\": [ { \"Indicator\": \"filmesonlinegratis.net\",",
      "name": "{",
      "required": ""
    },
    {
      "description": "\"Type\": \"domain\", \"Vendor\": \"PassiveTotal\" },",
      "name": "\"Score\": 0,",
      "required": ""
    },
    {
      "description": "\"Indicator\": \"www.filmesonlinegratis.net\", \"Score\": 0, \"Type\": \"domain\",",
      "name": "{",
      "required": ""
    },
    {
      "description": "} ], \"Domain\": [",
      "name": "\"Vendor\": \"PassiveTotal\"",
      "required": ""
    },
    {
      "description": "\"Name\": \"filmesonlinegratis.net\" }, {",
      "name": "{",
      "required": ""
    },
    {
      "description": "} ], \"PassiveTotal\": {",
      "name": "\"Name\": \"www.filmesonlinegratis.net\"",
      "required": ""
    },
    {
      "description": "{ \"attributeType\": \"GoogleAnalyticsTrackingId\", \"attributeValue\": \"ua-70630818-3\",",
      "name": "\"Tracker\": [",
      "required": ""
    },
    {
      "description": "\"hostname\": \"filmesonlinegratis.net\", \"lastSeen\": \"2020-06-14 19:43:28\" },",
      "name": "\"firstSeen\": \"2016-10-14 10:16:38\",",
      "required": ""
    },
    {
      "description": "\"attributeType\": \"GoogleAnalyticsAccountNumber\", \"attributeValue\": \"ua-70630818\", \"firstSeen\": \"2016-10-14 10:16:38\",",
      "name": "{",
      "required": ""
    },
    {
      "description": "\"lastSeen\": \"2020-06-14 19:43:28\" }, {",
      "name": "\"hostname\": \"filmesonlinegratis.net\",",
      "required": ""
    },
    {
      "description": "\"attributeValue\": \"ua-11598035\", \"firstSeen\": \"2012-03-07 05:53:50\", \"hostname\": \"www.filmesonlinegratis.net\",",
      "name": "\"attributeType\": \"GoogleAnalyticsAccountNumber\",",
      "required": ""
    },
    {
      "description": "}, { \"attributeType\": \"GoogleAnalyticsTrackingId\",",
      "name": "\"lastSeen\": \"2016-10-13 15:38:35\"",
      "required": ""
    },
    {
      "description": "\"firstSeen\": \"2012-03-07 05:53:50\", \"hostname\": \"www.filmesonlinegratis.net\", \"lastSeen\": \"2016-10-13 15:38:35\"",
      "name": "\"attributeValue\": \"ua-11598035-1\",",
      "required": ""
    },
    {
      "description": "{ \"attributeType\": \"GoogleAnalyticsTrackingId\", \"attributeValue\": \"ua-11598035-1\",",
      "name": "},",
      "required": ""
    },
    {
      "description": "\"hostname\": \"filmesonlinegratis.net\", \"lastSeen\": \"2016-09-13 03:54:34\" },",
      "name": "\"firstSeen\": \"2014-02-11 01:30:40\",",
      "required": ""
    },
    {
      "description": "\"attributeType\": \"GoogleAnalyticsAccountNumber\", \"attributeValue\": \"ua-11598035\", \"firstSeen\": \"2014-02-11 01:30:40\",",
      "name": "{",
      "required": ""
    },
    {
      "description": "\"lastSeen\": \"2016-09-13 03:54:34\" }, {",
      "name": "\"hostname\": \"filmesonlinegratis.net\",",
      "required": ""
    },
    {
      "description": "\"attributeValue\": \"25.media\", \"firstSeen\": \"2016-07-02 00:46:33\", \"hostname\": \"www.filmesonlinegratis.net\",",
      "name": "\"attributeType\": \"TumblrId\",",
      "required": ""
    },
    {
      "description": "}, { \"attributeType\": \"FacebookId\",",
      "name": "\"lastSeen\": \"2016-09-02 11:09:30\"",
      "required": ""
    },
    {
      "description": "\"firstSeen\": \"2012-11-27 06:06:44\", \"hostname\": \"www.filmesonlinegratis.net\", \"lastSeen\": \"2015-09-26 05:52:23\"",
      "name": "\"attributeValue\": \"filmesog\",",
      "required": ""
    },
    {
      "description": "{ \"attributeType\": \"FacebookId\", \"attributeValue\": \"filmesog\",",
      "name": "},",
      "required": ""
    },
    {
      "description": "\"hostname\": \"filmesonlinegratis.net\", \"lastSeen\": \"2015-09-24 05:12:39\" },",
      "name": "\"firstSeen\": \"2014-02-11 01:30:40\",",
      "required": ""
    },
    {
      "description": "\"attributeType\": \"WhosAmungUsId\", \"attributeValue\": \"6cdg\", \"firstSeen\": \"2012-03-07 05:53:50\",",
      "name": "{",
      "required": ""
    },
    {
      "description": "\"lastSeen\": \"2012-03-07 16:00:45\" } ]",
      "name": "\"hostname\": \"www.filmesonlinegratis.net\",",
      "required": ""
    },
    {
      "description": "}",
      "name": "}",
      "required": ""
    },
    {
      "description": "Context Example",
      "name": "Script Example",
      "required": ""
    }
  ],
  "retrieved_at": "2026-04-22T15:02:53+00:00",
  "source_title": "RiskIQPassiveTotalTrackersScript",
  "source_url": "https://xsoar.pan.dev/docs/reference/scripts/risk-iq-passive-total-trackers-script"
}
